frenetix-0.4.0.dist-info/WHEEL
frenetix-0.4.0.dist-info/RECORD
frenetix-0.4.0.dist-info/METADATA
frenetix-0.4.0.dist-info/licenses/LICENSE
frenetix.libs/libgfortran-a8535147.so.5.0.0
frenetix.libs/libquadmath-e2ac3af2.so.0.0.0
frenetix.libs/libgomp-65f46eca.so.1.0.0
frenetix/_version.py
frenetix/py.typed
frenetix/_version.pyi
frenetix/.gitkeep
frenetix/_frenetix.cpython-311-i386-linux-gnu.so
frenetix/__init__.py
frenetix/_frenetix/__init__.pyi
frenetix/_frenetix/trajectory_functions/__init__.pyi
frenetix/_frenetix/trajectory_functions/feasability_functions/__init__.pyi
frenetix/_frenetix/trajectory_functions/cost_functions/__init__.pyi
frenetix/trajectory_functions/__init__.py
frenetix/trajectory_functions/feasability_functions/__init__.py
frenetix/trajectory_functions/cost_functions/__init__.py
