Metadata-Version: 2.1
Name: frenetix
Version: 0.4.0
Summary: C++-accelerated Frenet Trajectory Planning Handler
Author-Email: Georg Schmalhofer <georg.schmalhofer@tum.de>, Tobias Markus <tobias.markus@tum.de>, Rainer Trauth <rainer.trauth@tum.de>
Maintainer-Email: Rainer Trauth <rainer.trauth@tum.de>
License: LGPL-3.0-or-later
Project-URL: Homepage, https://github.com/TUM-AVS/Frenetix
Project-URL: Bug tracker, https://github.com/TUM-AVS/Frenetix/issues
Requires-Python: <3.13,>=3.8
Requires-Dist: numpy>=1.20
